TriplePair/TriplePair.py
TriplePair/TriplePairTests.py
TriplePair-1.dist-info/LICENSE
TriplePair-1.dist-info/METADATA
TriplePair-1.dist-info/WHEEL
TriplePair-1.dist-info/entry_points.txt
TriplePair-1.dist-info/top_level.txt
TriplePair-1.dist-info/RECORD
